ignf_gpf_sdk/Errors.py
ignf_gpf_sdk/__init__.py
ignf_gpf_sdk/__main__.py
ignf_gpf_sdk/py.typed
ignf_gpf_sdk/_conf/default.ini
ignf_gpf_sdk/_conf/json_schemas/upload_descriptor_file.json
ignf_gpf_sdk/_conf/json_schemas/workflow.json
ignf_gpf_sdk/_data/datasets/1_dataset_vector/CANTON.md5
ignf_gpf_sdk/_data/datasets/1_dataset_vector/CANTON_style.sld
ignf_gpf_sdk/_data/datasets/1_dataset_vector/upload_descriptor.json
ignf_gpf_sdk/_data/datasets/1_dataset_vector/CANTON/CANTON.cpg
ignf_gpf_sdk/_data/datasets/1_dataset_vector/CANTON/CANTON.dbf
ignf_gpf_sdk/_data/datasets/1_dataset_vector/CANTON/CANTON.prj
ignf_gpf_sdk/_data/datasets/1_dataset_vector/CANTON/CANTON.shp
ignf_gpf_sdk/_data/datasets/1_dataset_vector/CANTON/CANTON.shx
ignf_gpf_sdk/_data/datasets/2_dataset_archive/CANTON.md5
ignf_gpf_sdk/_data/datasets/2_dataset_archive/upload_descriptor.json
ignf_gpf_sdk/_data/datasets/2_dataset_archive/CANTON/CANTON.zip
ignf_gpf_sdk/_data/datasets/5_dataset_maj_bd_gpf/installation.sld
ignf_gpf_sdk/_data/datasets/5_dataset_maj_bd_gpf/upload_descriptor.json
ignf_gpf_sdk/_data/datasets/5_dataset_maj_bd_gpf/lot_1/installation-init.sql
ignf_gpf_sdk/_data/datasets/5_dataset_maj_bd_gpf/lot_2/installation.gpkg
ignf_gpf_sdk/_data/datasets/5_dataset_maj_bd_gpf/lot_3/installation.csv
ignf_gpf_sdk/_data/datasets/5_dataset_maj_bd_gpf/lot_3/installation.csvt
ignf_gpf_sdk/_data/workflows/generic_archive.jsonc
ignf_gpf_sdk/_data/workflows/generic_joincache.jsonc
ignf_gpf_sdk/_data/workflows/generic_maj_bdd.jsonc
ignf_gpf_sdk/_data/workflows/generic_moissonnage.jsonc
ignf_gpf_sdk/_data/workflows/generic_raster.jsonc
ignf_gpf_sdk/_data/workflows/generic_vecteur.jsonc
ignf_gpf_sdk/auth/Authentifier.py
ignf_gpf_sdk/auth/Errors.py
ignf_gpf_sdk/auth/Token.py
ignf_gpf_sdk/auth/__init__.py
ignf_gpf_sdk/helper/FileHelper.py
ignf_gpf_sdk/helper/JsonHelper.py
ignf_gpf_sdk/helper/PrintLogHelper.py
ignf_gpf_sdk/helper/__init__.py
ignf_gpf_sdk/io/ApiRequester.py
ignf_gpf_sdk/io/Color.py
ignf_gpf_sdk-0.1.16.dist-info/entry_points.txt
ignf_gpf_sdk-0.1.16.dist-info/LICENSE
ignf_gpf_sdk-0.1.16.dist-info/WHEEL
ignf_gpf_sdk-0.1.16.dist-info/METADATA
ignf_gpf_sdk-0.1.16.dist-info/RECORD
