Metadata-Version: 2.1
Name: ignf_gpf_sdk
Version: 0.1.16
Summary: SDK Python pour simplifier l'utilisation de l'API Entrepôt de la Géoplateforme.
Author-email: Valentin Sasyan <valentin.sasyan@ign.fr>
Requires-Python: >=3.8
Classifier: License :: OSI Approved :: MIT License
Classifier: Programming Language :: Python :: 3
Classifier: Programming Language :: Python :: 3.8
Requires-Dist: requests>=2.6
Requires-Dist: configparser
Requires-Dist: types-requests
Requires-Dist: jsonschema
Requires-Dist: jsonc-parser
Requires-Dist: toml
Requires-Dist: types-toml
Requires-Dist: python-dateutil
Requires-Dist: types-python-dateutil
Requires-Dist: pyotp
Requires-Dist: requests_toolbelt
Requires-Dist: mkdocs-material==9.* ; extra == "doc"
Requires-Dist: mkdocstrings[python] ; extra == "doc"
Requires-Dist: black<23 ; extra == "test"
Requires-Dist: pylint==2.17 ; extra == "test"
Requires-Dist: mypy==0.950 ; extra == "test"
Requires-Dist: requests_mock ; extra == "test"
Requires-Dist: coverage ; extra == "test"
Project-URL: Documentation, https://github.com/ignf-sidc/ignf-gpf-sdk
Project-URL: Source, https://github.com/ignf-sidc/ignf-gpf-sdk
Provides-Extra: doc
Provides-Extra: test
